AnDanFirstTaskTest/__init__.py
AnDanFirstTaskTest/testfile.py
AnDanFirstTaskTest-0.7.0.dist-info/METADATA
AnDanFirstTaskTest-0.7.0.dist-info/WHEEL
AnDanFirstTaskTest-0.7.0.dist-info/top_level.txt
AnDanFirstTaskTest-0.7.0.dist-info/RECORD
